pcalf/.DS_Store
pcalf/__init__.py
pcalf/__pycache__/__init__.cpython-39.pyc
pcalf/core/PcalfDB.py
pcalf/core/PcalfSnake.py
pcalf/core/__init__.py
pcalf/core/biohmm.py
pcalf/core/bioseq.py
pcalf/core/log.py
pcalf/core/pcalf_db_scheme.sql
pcalf/core/search.py
pcalf/core/__pycache__/PcalfDB.cpython-39.pyc
pcalf/core/__pycache__/PcalfSnake.cpython-39.pyc
pcalf/core/__pycache__/__init__.cpython-39.pyc
pcalf/core/__pycache__/biohmm.cpython-39.pyc
pcalf/core/__pycache__/bioseq.cpython-39.pyc
pcalf/core/__pycache__/log.cpython-39.pyc
pcalf/core/__pycache__/search.cpython-39.pyc
pcalf/datas/Gly1.hmm
pcalf/datas/Gly1.msa.fa
pcalf/datas/Gly2.hmm
pcalf/datas/Gly2.msa.fa
pcalf/datas/Gly3.hmm
pcalf/datas/Gly3.msa.fa
pcalf/datas/GlyX3.hmm
pcalf/datas/GlyX3.msa.fa
pcalf/datas/__init__.py
pcalf/datas/accession.txt
pcalf/datas/all.hmm
pcalf/datas/calcyanin.fasta
pcalf/datas/nterdb.fasta
pcalf/datas/nterdb.ref.tsv
pcalf/datas/nterdb.tsv
pcalf/datas/__pycache__/__init__.cpython-39.pyc
pcalf/pcalf.egg-info/PKG-INFO
pcalf/pcalf.egg-info/SOURCES.txt
pcalf/pcalf.egg-info/dependency_links.txt
pcalf/pcalf.egg-info/not-zip-safe
pcalf/pcalf.egg-info/requires.txt
pcalf/pcalf.egg-info/top_level.txt
pcalf/report/Report.ipynb
pcalf/report/__init__.py
pcalf/report/pcalf.svg
pcalf/report/render.py
pcalf/report/template.css
pcalf/report/template.html
pcalf/report/template.js
pcalf/report/.ipynb_checkpoints/Report-checkpoint.ipynb
pcalf/report/__pycache__/__init__.cpython-39.pyc
pcalf/report/__pycache__/render.cpython-39.pyc
pcalf/workflow/.DS_Store
pcalf/workflow/.ipynb_checkpoints/Report-checkpoint.ipynb
pcalf/workflow/annotate/.DS_Store
pcalf/workflow/annotate/Snakefile
pcalf/workflow/annotate/__init__.py
pcalf/workflow/annotate/__pycache__/__init__.cpython-39.pyc
pcalf/workflow/annotate/config/.DS_Store
pcalf/workflow/annotate/config/config.yaml
pcalf/workflow/annotate/envs/.DS_Store
pcalf/workflow/annotate/envs/biopython_1.79.yaml
pcalf/workflow/annotate/envs/checkm.yaml
pcalf/workflow/annotate/envs/gtdbtk_2.1.yaml
pcalf/workflow/annotate/envs/ncbi_dataset_14.14.0.yaml
pcalf/workflow/annotate/rules/.DS_Store
pcalf/workflow/annotate/rules/checkm.smk
pcalf/workflow/annotate/rules/gtdbtk.smk
pcalf-1.2.6.dist-info/LICENSE.txt
pcalf-1.2.6.dist-info/METADATA
pcalf-1.2.6.dist-info/WHEEL
pcalf-1.2.6.dist-info/top_level.txt
pcalf-1.2.6.dist-info/RECORD
