Metadata-Version: 2.1
Name: pcalf
Version: 1.2.6
Summary: Search calcyanin in a set of amino acid sequences
Home-page: https://github.com/K2SOHIGH/pcalf
Author: Maxime Millet
Author-email: maxime.luc.millet@gmail.com
License: MIT
Classifier: Programming Language :: Python :: 3
Classifier: License :: OSI Approved :: MIT License
Classifier: Operating System :: OS Independent
Requires-Python: >=3.1
License-File: LICENSE.txt
Requires-Dist: pyhmmer
Requires-Dist: biopython
Requires-Dist: numpy
Requires-Dist: pyyaml
Requires-Dist: snakemake
Requires-Dist: pandas
Requires-Dist: tqdm
Requires-Dist: plotly
Requires-Dist: python-igraph
